{
  "101":
  {
    "Понедельник":
    {
      "first":"Английский язык, каб. 202, 404",
      "second":"Алгебра и начала анализа, каб. 103",
      "third":"Русский язык, каб. 305",
      "fourth":"Обществознание, каб. 203"
    },
    "Вторник":
    {
      "first":"Физика, каб. 208",
      "second":"Химия, каб. 307",
      "third":"Литература, каб. 305",
      "fourth":"Биология, каб. 203"
    },
    "Среда":
    {
      "first":"Английский язык(2 подгруппа), каб. 404 - Физика(1 подгруппа), каб. 208",
      "second":"География, каб. 307",
      "third":"Конфликтология и основы самоменеджмента, каб. 305",
      "fourth":"Практикум по решению задач повышенного уровня по физике(1 подгруппа), каб. 208 - Практикум по решению задач повышенного уровня по  математике(2 подгруппа), каб. 103"
    },
    "Четверг":
    {
      "first":"Геометрия, каб. 103",
      "second":"Практикум по решению задач повышенного уровня по  математике(1 подгруппа), каб. 103 - Практикум по решению задач повышенного уровня по физике(2 подгруппа), каб. 208",
      "third":"Литература",
      "fourth":"Деловой английский язык, каб. 202, 404"
    },
    "Пятница":
    {
      "first":"Грамматика. Текст. Стили речи(1 подгруппа), каб. 305 - Лабораторный практикум по физике(2 подгруппа), каб. 311",
      "second":"Физическая культура",
      "third":"Физика(1 подгруппа), каб. 208 - Информатика и ИКТ(2 подгруппа),каб. 105",
      "fourth":"История, каб. 205"
    },
    "Суббота":
    {
      "first":"Параметры в математике, каб. 104",
      "second":"Информатика и ИКТ(1 подгруппа), каб. 105 - Физика(2 подгруппа), каб. 204",
      "third":"Алгебра и начала анализа, каб. 103",
      "fourth":""
    }
  },
  "102":
  {
    "Понедельник":
    {
      "first":"Русский язык, каб. 305",
      "second":"Обществознание, каб. 205",
      "third":"Алгебра и начала анализа, каб. 103",
      "fourth":""
    },
    "Вторник":
    {
      "first":"Практикум по решению задач повышенного уровня по математике (1 подгруппа), каб. 103",
      "second":"Английский язык(1 подгруппа), каб. 404 - Физика(2 подгруппа), каб. 208",
      "third":"Химия, каб. 307",
      "fourth":"Физика, каб. 208"
    },
    "Среда":
    {
      "first":"Физическая культура",
      "second":"Физика(1 подгруппа), каб. 208 - Информатика и ИКТ(2 подгруппа), каб. 105",
      "third":"Геометрия, каб. 103",
      "fourth":"География, каб. 307"
    },
    "Четверг":
    {
      "first":"Литература, каб. 305",
      "second":"Английский, каб. 202, 404",
      "third":"Практикум по решению задач повышенного уровня по физике(1 подгруппа), каб. 208 - Лабораторный практикум по физике(2 подгруппа), каб. 311",
      "fourth":"Практикум по решению задач повышенного уровня по математике(2 подгруппа), каб. 103 - Грамматика. Текст. Стили речи(1 подгруппа), каб. 208"
    },
    "Пятница":
    {
      "first":"Биология, каб. 307",
      "second":"История, каб. 205",
      "third":"Литература, каб. 305",
      "fourth":"Практикум по решению задач повышенного уровня по физике(2 подгруппа), каб. 208"
    },
    "Суббота":
    {
      "first":"Информатика и ИКТ(1 подгруппа), каб. 105 - Физика(2 подгруппа), каб. 208",
      "second":"Алгебра и начала анализа, каб. 103",
      "third":"",
      "fourth":""
    }
  },
  "103":
  {
    "Понедельник":
    {
      "first":"Физика, каб. 307",
      "second":"Алгебра и начала анализа, каб. 301",
      "third":"Информатика и ИКТ(2 подгруппа), каб. 105 - Физика(1 подгруппа), каб. 311",
      "fourth":"Практикум по решению задач повышенного уровня по физике(2 подгруппа), каб. 311 - Грамматика. Текст. Стили речи(1 подгруппа), каб. 305"
    },
    "Вторник":
    {
      "first":"Литература, каб. 305",
      "second":"Физика(2 подгруппа), каб. 311 - Информатика и ИКТ(1 подгруппа), каб. 105",
      "third":"Английский язык(2 подгруппа), каб. 404 - Физика(1 подгруппа), каб. 311",
      "fourth":"Химия, каб. 307"
    },
    "Среда":
    {
      "first":"Обществознание, каб. 203",
      "second":"Физическая культура",
      "third":"География, каб. 301",
      "fourth":"История, каб. 205"
    },
    "Четверг":
    {
      "first":"Геометрия, каб. 301",
      "second":"Классный час, каб. 301",
      "third":"Английский язык, каб. 202, 404",
      "fourth":"Деловой английский язык, каб. 202, 404 - Немецкий язык, каб. 205"
    },
    "Пятница":
    {
      "first":"Алгебра и начала анализа, каб. 301",
      "second":"Русский язык, каб. 305",
      "third":"Практикум по решению задач повышенного уровня по физике(1 подгруппа), каб. 311 - Практикум по решению задач повышенного уровня по математике(2 подгруппа), каб. 301",
      "fourth":"Практикум по решению задач повышенного уровня по математике(1 подгруппа), каб. 301"
    },
    "Суббота":
    {
      "first":"Биология, каб. 307",
      "second":"Параметры в математике, каб. 104",
      "third":"Лабораторный практикум по физике, каб. 311",
      "fourth":""
    }
  },
  "104":
  {
    "Понедельник":
    {
      "first":"Алгебра и начала анализа, каб. 103",
      "second":"Русский язык, каб. 305",
      "third":"Английский язык, каб. 202, 204",
      "fourth":"Практикум по решению задач повышенного уровня по физике(1 подгруппа), каб. 206 - Практикум по решению задач повышенного уровня по математике(2 подгруппа), каб. 301",
      "fourth":"Практикум по решению задач повышенного уровня по математике(2 подгруппа), каб. 103"
    },
    "Вторник":
    {
      "first":"Химия, каб. 307",
      "second":"Литература, каб. 305",
      "third":"Биология, каб. 203",
      "fourth":"Физическая культура"
    },
    "Среда":
    {
      "first":"Геометрия, каб. 103",
      "second":"История, каб. 205",
      "third":"Английский язык(2 подгруппа), каб. 404 - Физика(1 подгруппа), каб. 206",
      "fourth":"Конфликтология и основы самоменеджмента, каб. 305"
    },
    "Четверг":
    {
      "first":"Физика, каб. 206",
      "second":"Литература, каб. 305",
      "third":"Практикум по решению задач повышенного уровня по математике(1 подгруппа), каб. 103 - Практикум по решению задач повышенного уровня по физике(2 подгруппа), каб. 206",
      "fourth":"Деловой английский язык, каб. 202, 404 - Немецкий язык, каб. 205"
    },
    "Пятница":
    {
      "first":"Физика(1 подгруппа), каб. 206 - Информатика и ИКТ(2 подгруппа), каб. 105",
      "second":"Информатика и ИКТ(1 подгруппа), каб. 105 - Физика(1 подгруппа), каб. 208",
      "third":"География, каб. 307",
      "fourth":"Грамматика. Текст. Стили речи(1 подгруппа), каб. 305 - Лабораторный практикум по физике(2 подгруппа), каб. 311"
    },
    "Суббота":
    {
      "first":"Алгебра и начала анализа, каб. 103",
      "second":"Обществознание, каб. 203",
      "third":"Классный час, каб. 103",
      "fourth":""
    }
  },
  "111":
  {
    "Понедельник":
    {
      "first":"Алгебра и начала анализа, каб. 304",
      "second":"Английский язык, каб. 202, 404",
      "third":"Литература, каб. 108",
      "fourth":"Физика, каб. 209"
    },
    "Вторник":
    {
      "first":"Информатика и ИКТ(1 подгруппа), каб. 105 - Физика(2 подгруппа), каб. 209",
      "second":"Физическая культура",
      "third":"Русский язык, каб. 108",
      "fourth":"История, каб. 205"
    },
    "Среда":
    {
      "first":"Геометрия, каб. 304",
      "second":"Техническое черчение, каб. 105",
      "third":"Информатика и ИКТ(2 подгруппа), каб. 105 - Физика(1 подгруппа), каб. 209",
      "fourth":"Практикум по решению задач повышенного уровня по математике(1 подгруппа), каб. 304 - Практикум по решению задач повышенного уровня по физике(2 подгруппа), каб. 209"
    },
    "Четверг":
    {
      "first":"Физическая культура",
      "second":"Техническое черчение, каб. 105",
      "third":"Основы безопасности жизнидеятельности, каб. 106",
      "fourth":"Русский язык. Культура речи(1 подгруппа), каб. 108"
    },
    "Пятница":
    {
      "first":"Классный час, каб. 209",
      "second":"Алгебра и начала анализа, каб. 304",
      "third":"Физика(1 подгруппа), каб. 209 - Английский язык(2 подгруппа), каб. 202",
      "fourth":"Практикум по решению задач повышенного уровня по физике(1 подгруппа), каб. 209 - Практикум по решению задач повышенного уровня по математике(2 подгруппа), каб. 304"
    },
    "Суббота":
    {
      "first":"Механические и электромагнитные колебания и волны, каб. 104",
      "second":"Биология, каб. 307",
      "third":"Обществознание, каб. 203",
      "fourth":""
    }
  },
  "112":
  {
    "Понедельник":
    {
      "first":"Физика, каб. 209",
      "second":"Практикум по решению задач повышенного уровня по физике(1 подгруппа), каб. 209 - Практикум по решению задач повышенного уровня по математике(2 подгруппа), каб. 304",
      "third":"История, каб. 205",
      "fourth":"Английский язык, каб. 202, 404 - Немецкий язык, каб. 208"
    },
    "Вторник":
    {
      "first":"Физическая культура",
      "second":"Практикум по решению задач повышенного уровня по математике(1 подгруппа), каб. 304 - Практикум по решению задач повышенного уровня по физике(2 подгруппа), каб. 209",
      "third":"Информатика и ИКТ(2 подгруппа), каб. 105 - Физика(1 подгруппа), каб. 209",
      "fourth":"Русский язык. Культура речи(1 подгруппа), каб. 108"
    },
    "Среда":
    {
      "first":"Информатика и ИКТ(1 подгруппа), каб. 105 - Физика(2 подгруппа), каб. 209",
      "second":"Геометрия, каб. 304",
      "third":"Техническое черчение, каб. 108",
      "fourth":"Обществознание, каб. 203"
    },
    "Четверг":
    {
      "first":"",
      "second":"Алгебра и начала анализа, каб. 304",
      "third":"Литература, каб. 108",
      "fourth":"Техническое черчение, каб. 105"
    },
    "Пятница":
    {
      "first":"Алгебра и начала анализа, каб. 304",
      "second":"Физика(2 подгруппа), каб. 209 - Английский язык(1 подгруппа), каб. 202",
      "third":"Русский язык, каб. 108",
      "fourth":"Основы безопасности жизнидеятельности, каб. 106"
    },
    "Суббота":
    {
      "first":"Физическая культура",
      "second":"Механические и электромагнитные колебания и волны, каб. 104",
      "third":"Биология, каб. 307",
      "fourth":""
    }
  },
  "113":
  {
    "Понедельник":
    {
      "first":"Информатика и ИКТ(1 подгруппа), каб. 105 - Физика(2 подгруппа), каб. 206",
      "second":"Информатика и ИКТ(2 подгруппа), каб. 105 - Физика(1 подгруппа), каб. 206",
      "third":"Алгебра и начала анализа, каб. 304",
      "fourth":"Немецкий язык, каб. 208"
    },
    "Вторник":
    {
      "first":"Английский язык, каб. 202,204 - Немецкий язык, каб. 205",
      "second":"Русский язык,каб. 108",
      "third":"Основы безопасности и жизнидеятельности, каб. 106",
      "fourth":"Практикум по решению задач повышенного уровня по математике(1 подгруппа), каб. 304 - Практикум по решению задач повышенного уровня по физике(2 подгруппа), каб. 206"
    },
    "Среда":
    {
      "first":"Техническое черчение, каб. 108",
      "second":"Английский язык(1 подгруппа), каб. 404 - Физика(2 подгруппа), каб. 206",
      "third":"Геометрия, каб. 304",
      "fourth":"Физика, каб. 206"
    },
    "Четверг":
    {
      "first":"Техническое черчение, каб. 105",
      "second":"Литература, каб. 108",
      "third":"Алгебра и начала анализа, каб. 304",
      "fourth":"Практикум по решению задач повышенного уровня по математике(2 подгруппа), каб. 304 - Практикум по решению задач повышенного уровня по физике(1 подгруппа), каб. 206"
    },
    "Пятница":
    {
      "first":"Физическая культура",
      "second":"Биология, каб. 307",
      "third":"История, каб. 205",
      "fourth":"Русский язык. Культура речи(1 подгруппа), каб. 108"
    },
    "Суббота":
    {
      "first":"Обществознание, каб. 203",
      "second":"Физическая культура",
      "third":"Механические и электромагнитные колебания и волны",
      "fourth":""
    }
  },
  "114":
  {
    "Понедельник":
    {
      "first":"Алгебра и начала анализа, каб. 301",
      "second":"Литература, каб. 108",
      "third":"Физика(ФМ), каб. 209 - Экономика(БИ), каб. 203",
      "fourth":"Русский язык. Культура речи(1 подгруппа), каб. 108"
    },
    "Вторник":
    {
      "first":"Русский язык, каб. 108",
      "second":"Биология, каб. 205",
      "third":"История, каб. 205",
      "fourth":"Практикум по решению задач повышенного уровня по физике(ФМ), каб. 209 - Информатика и ИКТ(БИ), каб. 105"
    },
    "Среда":
    {
      "first":"Геометрия, каб. 301",
      "second":"Физика(ФМ), каб. 209 - Обществознание(БИ), каб. 203",
      "third":"Обществознание(ФМ), каб. 203 - Физика(БИ), каб. 208",
      "fourth":"Техническое черчение(ФМ), каб. 108"
    },
    "Четверг":
    {
      "first":"Английский язык, каб. 202, 404",
      "second":"Физическая культура",
      "third":"Техническое черчение(ФМ), каб. 105 - Практикум по решению задач повышенного уровня по математике(БИ), каб. 301",
      "fourth":"Практикум по решению задач повышенного уровня по математике(ФМ), каб. 301 - Основы политологии(БИ), каб. 203"
    },
    "Пятница":
    {
      "first":"Английский язык, каб. 202, 404",
      "second":"Алгебра и начала анализа, каб. 301",
      "third":"Основы безопасности и жизнидеятельности, каб. 106",
      "fourth":"Информатика и ИКТ(ФМ), каб. 105"
    },
    "Суббота":
    {
      "first":"",
      "second":"",
      "third":"Физическая культура",
      "fourth":"Механические и электромагнитные колебания и волны, каб. 104"
    }
  }
}